{"rule": {"cost_eur": 2969.44, "co2_tco2": 11.9789, "peak_mw": 2.0402, "terminal_soc_dev": 0.1125, "tie_violation_steps": 0, "tie_violation_mw": 0.0, "projection_mw": 34.3952, "decision_latency_s": 0.00348, "per_step_ms": 0.0362}, "nsga3": {"cost_eur": 3050.37, "co2_tco2": 11.1019, "peak_mw": 1.133, "terminal_soc_dev": 0.0, "tie_violation_steps": 0, "tie_violation_mw": 0.0, "projection_mw": 0.0, "decision_latency_s": 10.15584, "per_step_ms": 0.0005}, "rl": {"cost_eur": 2960.92, "co2_tco2": 14.2155, "peak_mw": 1.7368, "terminal_soc_dev": 0.0387, "tie_violation_steps": 0, "tie_violation_mw": 0.0, "projection_mw": 34.0619, "decision_latency_s": 0.03462, "per_step_ms": 0.3606}}